PstrYve/__init__.py
PstrYve/api.py
PstrYve/config.py
PstrYve/consts.py
PstrYve/enums.py
PstrYve/server.py
PstrYve/web_view.py
PstrYve-1.0.6.dist-info/LICENSE
PstrYve-1.0.6.dist-info/METADATA
PstrYve-1.0.6.dist-info/WHEEL
PstrYve-1.0.6.dist-info/top_level.txt
PstrYve-1.0.6.dist-info/RECORD
