Metadata-Version: 2.1
Name: PstrYve
Version: 1.0.6
Summary: Python Interface for Strava API
Home-page: https://github.com/matiyau/PstrYve
Author: Nishad Mandlik
Author-email: mandliksg@gmail.com
Project-URL: Documentation, https://PstrYve.rtfd.io
Project-URL: Bug Tracker, https://github.com/matiyau/PstrYve/issues
Classifier: Programming Language :: Python :: 3
Classifier: License :: OSI Approved :: MIT License
Classifier: Operating System :: OS Independent
Requires-Python: >=3.6
License-File: LICENSE
